__init__.py
pubmed_searchx/__init__.py
pubmed_searchx/__main__.py
pubmed_searchx/api.py
pubmed_searchx/gene_search.py
pubmed_searchx/parser.py
pubmed_searchx/utils.py
pubmed_searchx-0.1.6.dist-info/LICENSE
pubmed_searchx-0.1.6.dist-info/METADATA
pubmed_searchx-0.1.6.dist-info/WHEEL
pubmed_searchx-0.1.6.dist-info/top_level.txt
pubmed_searchx-0.1.6.dist-info/RECORD
