Metadata-Version: 2.1
Name: pubmed-searchx
Version: 0.1.6
Summary: Pubmed Search
Author-email: AnhND <nguyenanh.nda@gmail.com>
Classifier: Programming Language :: Python :: 3
Classifier: License :: OSI Approved :: MIT License
Classifier: Operating System :: OS Independent
Requires-Python: >=3.7
License-File: LICENSE
Requires-Dist: beautifulsoup4 >=4.12.2
Requires-Dist: lxml >=4.9.3
Requires-Dist: requests >=2.31.0
Requires-Dist: tqdm >=4.66.1
